deepeval/__init__.py
deepeval/_version.py
deepeval/api.py
deepeval/bulk_runner.py
deepeval/client.py
deepeval/constants.py
deepeval/dataset.py
deepeval/evaluator.py
deepeval/get_api_key.py
deepeval/key_handler.py
deepeval/pipeline.py
deepeval/query_generator.py
deepeval/retry.py
deepeval/run_test.py
deepeval/singleton.py
deepeval/test_case.py
deepeval/test_utils.py
deepeval/utils.py
deepeval/cli/__init__.py
deepeval/cli/cli_key_handler.py
deepeval/cli/main.py
deepeval/cli/test.py
deepeval/integrations/__init__.py
deepeval/integrations/langchain.py
deepeval/metrics/__init__.py
deepeval/metrics/alert_score.py
deepeval/metrics/answer_relevancy.py
deepeval/metrics/bertscore.py
deepeval/metrics/bertscore_metric.py
deepeval/metrics/bias_classifier.py
deepeval/metrics/bleu_metric.py
deepeval/metrics/cohere_reranker_metric.py
deepeval/metrics/conceptual_similarity.py
deepeval/metrics/entailment_metric.py
deepeval/metrics/factual_consistency.py
deepeval/metrics/metric.py
deepeval/metrics/overall_score.py
deepeval/metrics/randomscore.py
deepeval/metrics/ranking_similarity.py
deepeval/metrics/toxic_classifier.py
evals/__init__.py
evals/_version.py
evals/api.py
evals/bulk_runner.py
evals/client.py
evals/pipeline.py
evals/query_generator.py
evals/test_case.py
evals/test_utils.py
evals/utils.py
evals/metrics/__init__.py
evals/metrics/bertscore.py
evals/metrics/cohere_reranker_metric.py
evals/metrics/entailment_metric.py
evals/metrics/metric.py
evals/metrics/randomscore.py
tests/__init__.py
tests/test_alert_score.py
tests/test_answer_relevancy.py
tests/test_bert_score.py
tests/test_bias.py
tests/test_bulk_runner.py
tests/test_cli.py
tests/test_clients.py
tests/test_custom_metric.py
tests/test_dataset.py
tests/test_factual_consistency.py
tests/test_metric.py
tests/test_overall_score.py
tests/test_quickstart.py
tests/test_sample.py
tests/test_similar_ranking.py
tests/test_test_case.py
tests/test_toxic.py
tests/utils.py
testllm-0.14.1.dist-info/LICENSE
testllm-0.14.1.dist-info/METADATA
testllm-0.14.1.dist-info/WHEEL
testllm-0.14.1.dist-info/entry_points.txt
testllm-0.14.1.dist-info/top_level.txt
testllm-0.14.1.dist-info/RECORD
