Metadata-Version: 2.1
Name: testllm
Version: 0.14.1
Summary: Deep eval provides evaluation platform to accelerate development of LLMs and Agents
Home-page: https://github.com/mr-gpt/deepeval
Author: Confident AI
Author-email: jacky@twilix.io
License-File: LICENSE
Requires-Dist: requests
Requires-Dist: tqdm
Requires-Dist: transformers
Requires-Dist: pytest
Requires-Dist: tabulate
Requires-Dist: sentence-transformers
Requires-Dist: typer
Requires-Dist: rich
Requires-Dist: protobuf <=3.20.5
Requires-Dist: pandas
Provides-Extra: bias
Requires-Dist: tensorflow ; extra == 'bias'
Requires-Dist: Dbias ; extra == 'bias'
Provides-Extra: dev
Requires-Dist: black ; extra == 'dev'
Provides-Extra: toxic
Requires-Dist: detoxify ; extra == 'toxic'
